pyDSlib/__init__.py
pyDSlib/_plot_imgs.py
pyDSlib/file_utils.py
pyDSlib/git.py
pyDSlib/img.py
pyDSlib/kaggle.py
pyDSlib/plot.py
pyDSlib/summary_tables.py
pyDSlib/video.py
pyDSlib/ML/__init__.py
pyDSlib/ML/_devices.py
pyDSlib/ML/NeuralNet/Bert.py
pyDSlib/ML/NeuralNet/Conv2D.py
pyDSlib/ML/NeuralNet/Conv2D_AutoEncoder.py
pyDSlib/ML/NeuralNet/DenseNet.py
pyDSlib/ML/NeuralNet/__init__.py
pyDSlib/ML/NeuralNet/_callbacks.py
pyDSlib/ML/NeuralNet/_search.py
pyDSlib/ML/NeuralNet/plot.py
pyDSlib/ML/NeuralNet/utils.py
pyDSlib/ML/NeuralNet/RCNN/__init__.py
pyDSlib/ML/NeuralNet/RCNN/mask/__init__.py
pyDSlib/ML/NeuralNet/RCNN/mask/config.py
pyDSlib/ML/NeuralNet/RCNN/mask/model.py
pyDSlib/ML/NeuralNet/RCNN/mask/parallel_model.py
pyDSlib/ML/NeuralNet/RCNN/mask/utils.py
pyDSlib/ML/NeuralNet/RCNN/mask/visualize.py
pyDSlib/ML/NeuralNet/RCNN/mask/pretrained/__init__.py
pyDSlib/ML/NeuralNet/RCNN/mask/pretrained/coco.py
pyDSlib/ML/dask_ml_extend/__init__.py
pyDSlib/ML/dask_ml_extend/model_selection/__init__.py
pyDSlib/ML/dask_ml_extend/model_selection/_search.py
pyDSlib/ML/inspection/__init__.py
pyDSlib/ML/inspection/_unique.py
pyDSlib/ML/inspection/compare.py
pyDSlib/ML/inspection/feature_importance.py
pyDSlib/ML/inspection/maximize_success.py
pyDSlib/ML/inspection/plot.py
pyDSlib/ML/model_selection/__init__.py
pyDSlib/ML/model_selection/_search.py
pyDSlib/ML/model_selection/default_models_dict.py
pyDSlib/ML/postprocessing/__init__.py
pyDSlib/ML/postprocessing/transform.py
pyDSlib/ML/preprocessing/Impute.py
pyDSlib/ML/preprocessing/LabelEncode.py
pyDSlib/ML/preprocessing/OneHotEncode.py
pyDSlib/ML/preprocessing/Scale.py
pyDSlib/ML/preprocessing/_CorrCoeff.py
pyDSlib/ML/preprocessing/_PreprocessPipe.py
pyDSlib/ML/preprocessing/__init__.py
pyDSlib/ML/preprocessing/log.py
tests/ML/__init__.py
tests/ML/NeuralNet/__init__.py
tests/ML/NeuralNet/test_Bert.py
tests/ML/model_selection/__init__.py
tests/ML/model_selection/test_search.py
pyDSlib-0.3.5.dist-info/LICENSE
pyDSlib-0.3.5.dist-info/METADATA
pyDSlib-0.3.5.dist-info/WHEEL
pyDSlib-0.3.5.dist-info/top_level.txt
pyDSlib-0.3.5.dist-info/RECORD
